Metadata-Version: 2.1
Name: yolov5-thin
Version: 6.1.6
Summary: Packaged version of the Yolov5 object detector
Home-page: https://github.com/SethWen/yolov5-pip.git
Author: 
License: GPL
Keywords: machine-learning,deep-learning,ml,pytorch,YOLO,object-detection,vision,YOLOv3,YOLOv4,YOLOv5
Classifier: Development Status :: 5 - Production/Stable
Classifier: License :: OSI Approved :: GNU General Public License (GPL)
Classifier: Operating System :: OS Independent
Classifier: Intended Audience :: Developers
Classifier: Intended Audience :: Science/Research
Classifier: Programming Language :: Python :: 3
Classifier: Topic :: Software Development :: Libraries
Classifier: Topic :: Software Development :: Libraries :: Python Modules
Classifier: Topic :: Education
Classifier: Topic :: Scientific/Engineering
Classifier: Topic :: Scientific/Engineering :: Artificial Intelligence
Classifier: Topic :: Scientific/Engineering :: Image Recognition
Requires-Python: >=3.6
License-File: LICENSE
Requires-Dist: numpy>=1.18.5
Requires-Dist: opencv-python>=4.1.2
Requires-Dist: Pillow>=7.1.2
Requires-Dist: PyYAML>=5.3.1
Requires-Dist: torch>=1.10.0
Requires-Dist: torchvision>=0.8.1
Provides-Extra: tests
Requires-Dist: pytest; extra == "tests"
